setup.py
distributions_lettolabs/Binomialdistribution.py
distributions_lettolabs/Gaussiandistribution.py
distributions_lettolabs/Generaldistribution.py
distributions_lettolabs/__init__.py
distributions_lettolabs.egg-info/PKG-INFO
distributions_lettolabs.egg-info/SOURCES.txt
distributions_lettolabs.egg-info/dependency_links.txt
distributions_lettolabs.egg-info/not-zip-safe
distributions_lettolabs.egg-info/top_level.txt